holidays_ru/__init__.py
holidays_ru-0.1.dist-info/LICENSE
holidays_ru-0.1.dist-info/METADATA
holidays_ru-0.1.dist-info/WHEEL
holidays_ru-0.1.dist-info/top_level.txt
holidays_ru-0.1.dist-info/RECORD
